ssh_assistant/__about__.py
ssh_assistant/__init__.py
ssh_assistant/ssh_menu.py
ssh_assistant/utils.py
ssh_assistant/config/__init__.py
ssh_assistant/config/app_data.py
ssh_assistant/config/config.py
ssh_assistant/config/vim.py
ssh_assistant/menu/BaseMenu.py
ssh_assistant/menu/CategoriesMenu.py
ssh_assistant/menu/MainMenu.py
ssh_assistant/menu/SSHMenu.py
ssh_assistant/menu/__init__.py
ssh_assistant/ssh_data/__init__.py
ssh_assistant/ssh_data/ssh_config_data.py
ssh_assistant/ssh_data/ssh_data_loader.py
ssh_assistant-0.0.0a3.dist-info/METADATA
ssh_assistant-0.0.0a3.dist-info/WHEEL
ssh_assistant-0.0.0a3.dist-info/entry_points.txt
ssh_assistant-0.0.0a3.dist-info/RECORD
