Metadata-Version: 2.4
Name: ssh-assistant
Version: 0.0.0a3
Summary: SSH TUI Menu System and Related SSH Utilities
Project-URL: Source, https://gitlab.com/joeysbytes/ssh-assistant
Project-URL: Documentation, https://gitlab.com/joeysbytes/ssh-assistant/-/blob/main/README.md?ref_type=heads
Project-URL: Change_Log, https://gitlab.com/joeysbytes/ssh-assistant/-/blob/main/CHANGELOG?ref_type=heads
Project-URL: Issues, https://gitlab.com/joeysbytes/ssh-assistant/-/issues
Author-email: Joey Rockhold <ssh-assistant@joeysbytes.net>
License-Expression: Apache-2.0
Keywords: TUI,console,dialog,menu,ssh,terminal
Classifier: Development Status :: 3 - Alpha
Classifier: Environment :: Console
Classifier: Intended Audience :: System Administrators
Classifier: License :: OSI Approved :: Apache Software License
Classifier: Natural Language :: English
Classifier: Operating System :: POSIX :: Linux
Classifier: Programming Language :: Python
Classifier: Programming Language :: Python :: 3
Classifier: Programming Language :: Python :: 3 :: Only
Classifier: Programming Language :: Python :: 3.8
Classifier: Programming Language :: Python :: 3.9
Classifier: Programming Language :: Python :: 3.10
Classifier: Programming Language :: Python :: 3.11
Classifier: Programming Language :: Python :: 3.12
Classifier: Programming Language :: Python :: 3.13
Classifier: Topic :: System :: Systems Administration
Classifier: Topic :: Terminals
Classifier: Topic :: Utilities
Requires-Python: >=3.8
Requires-Dist: pythondialog~=3.5.3
